jsprint/__init__.py
jsprint-0.0.3.dist-info/LICENSE
jsprint-0.0.3.dist-info/METADATA
jsprint-0.0.3.dist-info/WHEEL
jsprint-0.0.3.dist-info/top_level.txt
jsprint-0.0.3.dist-info/RECORD
