Metadata-Version: 2.1
Name: jsprint
Version: 0.0.3
Summary: JSPrint, is a python package to bring a JS like way of logging to the console.
Author-email: NotAussie <notaussie@duck.com>
Project-URL: Homepage, https://github.com/notaussie/jsprint
Project-URL: Bug Tracker, https://github.com/notaussie/jsprint/issues
Classifier: Programming Language :: Python :: 3
Classifier: License :: OSI Approved :: MIT License
Classifier: Operating System :: OS Independent
Classifier: Development Status :: 3 - Alpha
Classifier: Intended Audience :: Developers
Requires-Python: >=3.10
License-File: LICENSE
